alamopy/__init__.py
alamopy/almain.py
alamopy/almconfidence.py
alamopy/almexec.py
alamopy/almlayer.py
alamopy/almopts.py
alamopy/almplot.py
alamopy/almread.py
alamopy/almutils.py
alamopy/almwrite.py
alamopy/example.py
alamopy/optsTest.py
alamopy/utilsTest.py
alamopy-0.2.2.dist-info/LICENSE
alamopy-0.2.2.dist-info/METADATA
alamopy-0.2.2.dist-info/WHEEL
alamopy-0.2.2.dist-info/top_level.txt
alamopy-0.2.2.dist-info/RECORD
